pywizlight/__init__.py
pywizlight/_version.py
pywizlight/bulb.py
pywizlight/bulblibrary.py
pywizlight/cli.py
pywizlight/discovery.py
pywizlight/exceptions.py
pywizlight/models.py
pywizlight/protocol.py
pywizlight/push_manager.py
pywizlight/rgbcw.py
pywizlight/scenes.py
pywizlight/utils.py
pywizlight/vec.py
pywizlight/tests/__init__.py
pywizlight/tests/fake_bulb.py
pywizlight/tests/test_bulb.py
pywizlight/tests/test_bulb_bad_json_1_0_0.py
pywizlight/tests/test_bulb_dimmable_white.py
pywizlight/tests/test_bulb_dimmable_white_1_11_7.py
pywizlight/tests/test_bulb_dimmable_white_1_8_0.py
pywizlight/tests/test_bulb_hero_1_23_70.py
pywizlight/tests/test_bulb_invalid_module_name.py
pywizlight/tests/test_bulb_light_strip_1_16_64.py
pywizlight/tests/test_bulb_light_strip_1_21_4.py
pywizlight/tests/test_bulb_light_strip_1_25_0.py
pywizlight/tests/test_bulb_missing_kelvin_range.py
pywizlight/tests/test_bulb_no_module_name.py
pywizlight/tests/test_bulb_rgbw_1_21_4.py
pywizlight/tests/test_bulb_rgbww_1_17_1.py
pywizlight/tests/test_bulb_socket.py
pywizlight/tests/test_bulb_socket_1_16_71.py
pywizlight/tests/test_bulb_squire_1_21_40.py
pywizlight/tests/test_bulb_turnable_white.py
pywizlight/tests/test_bulb_turnable_white_1_10_0.py
pywizlight/tests/test_bulb_turnable_white_1_18_0.py
pywizlight/tests/test_bulb_unknown_1_8_0.py
pywizlight/tests/test_bulb_wall_switch_1_16_68.py
pywizlight/tests/test_discovery.py
pywizlight/tests/test_push_manager.py
pywizlight/tests/test_scenes.py
pywizlight/tests/test_utils.py
pywizlight-0.6.2.dist-info/licenses/LICENSE
pywizlight-0.6.2.dist-info/METADATA
pywizlight-0.6.2.dist-info/WHEEL
pywizlight-0.6.2.dist-info/entry_points.txt
pywizlight-0.6.2.dist-info/top_level.txt
pywizlight-0.6.2.dist-info/RECORD
