Metadata-Version: 2.4
Name: pywizlight
Version: 0.6.2
Summary: A python connector for WiZ light bulbs (e.g SLV Play)
Home-page: https://github.com/sbidy/pywizlight
Author: Stephan Traub
Author-email: sbidy@hotmail.com
License: MIT
Classifier: Programming Language :: Python :: 3
Classifier: License :: OSI Approved :: MIT License
Classifier: Operating System :: OS Independent
Requires-Python: >=3.7
License-File: LICENSE
Requires-Dist: click
Dynamic: author
Dynamic: author-email
Dynamic: classifier
Dynamic: description
Dynamic: description-content-type
Dynamic: home-page
Dynamic: license
Dynamic: license-file
Dynamic: requires-dist
Dynamic: requires-python
Dynamic: summary
